microSHAP/__init__.py
microSHAP/microSHAPmodel.py
microSHAP-1.0.dist-info/METADATA
microSHAP-1.0.dist-info/WHEEL
microSHAP-1.0.dist-info/top_level.txt
microSHAP-1.0.dist-info/RECORD
