Metadata-Version: 2.1
Name: microSHAP
Version: 1.0
Summary: Microbiome AI
Home-page: UNKNOWN
Author: Karthik Sekaran
Author-email: <karthiksofficiallog@gmail.com>
License: UNKNOWN
Keywords: python,first package
Platform: UNKNOWN
Classifier: Development Status :: 3 - Alpha
Classifier: Intended Audience :: Education
Classifier: Programming Language :: Python :: 2
Classifier: Programming Language :: Python :: 3
Classifier: Operating System :: MacOS :: MacOS X
Classifier: Operating System :: Microsoft :: Windows
